Metadata-Version: 1.0
Name: homophones
Version: 1.0.0
Summary: Find homophones for a given word
Home-page: https://github.com/jbaber/homophones
Author: John Baber-Lucero
Author-email: pypi@frundle.com
License: GPLv3
Platform: UNKNOWN
